README.md
VERSION
loophost/__init__.py
loophost/bins/.keep
loophost/bins/loopproxy-darwin-amd64
loophost/bins/loopproxy-darwin-arm64
loophost/bins/loopproxy-linux-amd64
loophost/bins/loopproxy-linux-arm64
loophost/bins/loopproxy.exe
loophost/flingroute.py
loophost/installer.py
loophost/keys.py
loophost/plist/hub.plist.template
loophost/plist/loophost.plist.template
loophost/plist/ssh.plist.template
loophost/plist/tunnel.plist.template
loophost/postinstall.py
loophost/postinstall_two.py
loophost/static/fling-logo-dark.png
loophost/static/fling-logo-light.png
loophost/static/github-mark.png
loophost/static/logo-hc.txt
loophost/static/logo-square.png
loophost/templates/admin.html
loophost/templates/base.html
loophost/templates/local.html
loophost/templates/partials/apptable.html
loophost/templates/partials/upgrade.html
loophost/templates/start/base.html
loophost/tunnel.py
loophost/uninstall.py
loophost/utils_mac.py
loophost/win_hub.py
loophost/win_lp.py
setup.py
loophost-1.2.11.dist-info/METADATA
loophost-1.2.11.dist-info/WHEEL
loophost-1.2.11.dist-info/RECORD
